qpsolvers_benchmark/__init__.py
qpsolvers_benchmark/benchmark.py
qpsolvers_benchmark/exceptions.py
qpsolvers_benchmark/plot_metric.py
qpsolvers_benchmark/problem.py
qpsolvers_benchmark/report.py
qpsolvers_benchmark/results.py
qpsolvers_benchmark/run.py
qpsolvers_benchmark/shgeom.py
qpsolvers_benchmark/solver_issues.py
qpsolvers_benchmark/solver_settings.py
qpsolvers_benchmark/spdlog.py
qpsolvers_benchmark/test_set.py
qpsolvers_benchmark/tolerance.py
qpsolvers_benchmark/utils.py
qpsolvers_benchmark/version.py
qpsolvers_benchmark-1.2.0.dist-info/entry_points.txt
qpsolvers_benchmark-1.2.0.dist-info/LICENSE
qpsolvers_benchmark-1.2.0.dist-info/WHEEL
qpsolvers_benchmark-1.2.0.dist-info/METADATA
qpsolvers_benchmark-1.2.0.dist-info/RECORD
