Metadata-Version: 2.1
Name: qpsolvers_benchmark
Version: 1.2.0
Summary: Benchmark for quadratic programming solvers available in Python.
Keywords: quadratic programming,benchmark,solvers,numerical optimization
Author-email: Stéphane Caron <stephane.caron@normalesup.org>
Maintainer-email: Stéphane Caron <stephane.caron@normalesup.org>
Requires-Python: >=3.9
Classifier: Development Status :: 4 - Beta
Classifier: Intended Audience :: Developers
Classifier: Intended Audience :: Science/Research
Classifier: License :: OSI Approved :: Apache Software License
Classifier: Operating System :: OS Independent
Classifier: Programming Language :: Python :: 3.9
Classifier: Programming Language :: Python :: 3.10
Classifier: Programming Language :: Python :: 3.11
Classifier: Topic :: Scientific/Engineering :: Mathematics
Requires-Dist: clarabel >= 0.4.1
Requires-Dist: cvxopt >= 1.3.0
Requires-Dist: daqp >= 0.5.1
Requires-Dist: ecos >= 2.0.10
Requires-Dist: highspy >= 1.5.2
Requires-Dist: matplotlib >= 3.6.2
Requires-Dist: numpy >= 1.25.2
Requires-Dist: osqp >= 0.6.2
Requires-Dist: pandas >= 1.4.3
Requires-Dist: piqp >= 0.2.2
Requires-Dist: proxsuite >= 0.4.1
Requires-Dist: py-cpuinfo
Requires-Dist: qpsolvers >= 3.4.0
Requires-Dist: quadprog >= 0.1.11
Requires-Dist: scs >= 3.2.2
Requires-Dist: tabulate >= 0.9.0
Project-URL: Changelog, https://github.com/qpsolvers/qpsolvers_benchmark/blob/master/CHANGELOG.md
Project-URL: Source, https://github.com/qpsolvers/qpsolvers_benchmark
Project-URL: Tracker, https://github.com/qpsolvers/qpsolvers_benchmark/issues
